met_ml_project/__init__.py
met_ml_project/predict_pipeline.py
met_ml_project/train_pipeline.py
ml_project/__init__.py
ml_project/predict_pipeline.py
ml_project/train_pipeline.py
ml_project_met/__init__.py
ml_project_met/predict_pipeline.py
ml_project_met/train_pipeline.py
met_ml_project-0.1.2.dist-info/METADATA
met_ml_project-0.1.2.dist-info/WHEEL
met_ml_project-0.1.2.dist-info/top_level.txt
met_ml_project-0.1.2.dist-info/RECORD
