Metadata-Version: 2.1
Name: met-ml-project
Version: 0.1.2
Summary: MADE MLOps homework 1
Author: Denis Shibitov
Author-email: ttwtest1@gmail.com
Keywords: mlops,homework
Classifier: Natural Language :: English
Classifier: Programming Language :: Python
Requires-Python: >=3.7
Requires-Dist: sklearn (==0)
Requires-Dist: numpy (>=1.21.6)
Requires-Dist: pandas (>=1.2.0)
Requires-Dist: pandas-profiling (==3.4.0)
Requires-Dist: seaborn (==0.11.1)
Requires-Dist: click (==8.1.3)
Requires-Dist: marshmallow (==3.18.0)
Requires-Dist: marshmallow-dataclass (==8.5.9)
Requires-Dist: PyYAML (==6.0)
